iona_ops_library/__init__.py
iona_ops_library/_version.py
iona_ops_library/data_merger.py
iona_ops_library/field_change_logger.py
iona_ops_library/teams_message.py
iona_ops_library/utils_module.py
iona_ops_library-0.11.0.dist-info/METADATA
iona_ops_library-0.11.0.dist-info/WHEEL
iona_ops_library-0.11.0.dist-info/top_level.txt
iona_ops_library-0.11.0.dist-info/RECORD
