Metadata-Version: 2.4
Name: iona-ops-library
Version: 0.11.0
Summary: iona-ops library for common functions across DABs
Home-page: https://github.com/ION-Analytics/iona-ops
Author: Gary James
Author-email: Gary James <gary.james@iongroup.com>
License: MIT
Project-URL: Homepage, https://github.com/ION-Analytics/iona-ops
Requires-Python: >=3.8
Dynamic: author
Dynamic: home-page
Dynamic: requires-python
